gencode_by_sporniket-1.1.0.dist-info/METADATA
gencode_by_sporniket-1.1.0.dist-info/WHEEL
gencode_by_sporniket-1.1.0.dist-info/entry_points.txt
gencode_by_sporniket-1.1.0.dist-info/licenses/LICENSE
gencode_lib/__init__.py
gencode_lib/identifier.py
gencpp/__init__.py
gencpp/__main__.py
gencpp/argparsers.py
gencpp/cli.py
gencpp/generators/__init__.py
gencpp/generators/generators.py
gencpp/producers/__init__.py
gencpp/producers/blank.py
gencpp/producers/producer.py
gencpp/producers/sourcelib_testing.py
gencpp/templates.py
genpython/__init__.py
genpython/__main__.py
genpython/cli.py
zz_seed_lib/__init__.py
zz_seed_lib/whatever.py
zz_seed_top/__init__.py
zz_seed_top/__main__.py
zz_seed_top/cli.py
gencode_by_sporniket-1.1.0.dist-info/RECORD
