Metadata-Version: 2.1
Name: gencode-by-sporniket
Version: 1.1.0
Summary: Sporniket's toolbox for generating code
Keywords: code generator
Author-Email: Sporniket <sporniket.studio@gmail.com>
License: GPL-3.0-or-later
Project-URL: homepage, https://github.com/sporniket/gencode
Project-URL: repository, https://github.com/sporniket/gencode
Project-URL: bug-tracker, https://github.com/sporniket/gencode/issues
Requires-Python: >=3.9
Requires-Dist: Jinja2<3.2.0,>=3.1.0
